gallery/__init__.py
gallery/admin.py
gallery/models.py
gallery/specs/__init__.py
gallery/specs/base.py
gallery/specs/legacy.py
gallery/static/content/gallery/carousel.css
gallery/static/content/gallery/carousel.js
gallery/static/content/gallery/classic.css
gallery/static/content/gallery/gallery.js
gallery/static/content/gallery/jquery.infinitecarousel2.js
gallery/static/content/gallery/jquery.infinitecarousel2.min.js
gallery/static/content/gallery/jquery.panelgallery-2.0.0.js
gallery/static/content/gallery/jquery.panelgallery-2.0.0.min.js
gallery/static/content/gallery/panelgallery.js
gallery/static/content/gallery/product.css
gallery/static/content/gallery/product.js
gallery/static/content/gallery/slideshow.css
gallery/static/content/gallery/slideshow.js
gallery/static/content/gallery/images/caption.gif
gallery/static/content/gallery/images/leftright.gif
gallery/static/content/gallery/images/playpause.gif
gallery/templates/admin/gallery/add_category.html
gallery/templates/content/gallery/carousel.html
gallery/templates/content/gallery/image.html
gallery/templates/content/gallery/p.classic.html
gallery/templates/content/gallery/p.classiccaption.html
gallery/templates/content/gallery/p.classiclm.html
gallery/templates/content/gallery/p.classiclmcaption.html
gallery/templates/content/gallery/panel.html
gallery/templates/content/gallery/product.html
gallery/templates/content/gallery/slideshow.html
gallery/templatetags/__init__.py
gallery/templatetags/gallery_tags.py
feincms_gallery-1.3.1.dist-info/AUTHORS
feincms_gallery-1.3.1.dist-info/LICENSE
feincms_gallery-1.3.1.dist-info/METADATA
feincms_gallery-1.3.1.dist-info/WHEEL
feincms_gallery-1.3.1.dist-info/top_level.txt
feincms_gallery-1.3.1.dist-info/RECORD
