Metadata-Version: 2.1
Name: feincms-gallery
Version: 1.3.1
Summary: A gallery for FeinCMS
Home-page: https://github.com/feinheit/feincms_gallery
Author: Simon Baechler
Author-email: dev@feinheit.ch
License: BSD License
Platform: OS Independent
Classifier: Development Status :: 5 - Production/Stable
Classifier: Environment :: Web Environment
Classifier: Framework :: Django
Classifier: Intended Audience :: Developers
Classifier: License :: OSI Approved :: BSD License
Classifier: Operating System :: OS Independent
Classifier: Programming Language :: Python
Classifier: Topic :: Internet :: WWW/HTTP :: Dynamic Content
Classifier: Topic :: Software Development
Classifier: Topic :: Software Development :: Libraries :: Application Frameworks
License-File: LICENSE
License-File: AUTHORS
Requires-Dist: Django (>=3.2)
Requires-Dist: django-admin-ordering
Requires-Dist: FeinCMS (>=22.2.0)
